{"pdf_page": 159, "book_page": 141, "chapter": 4, "text": "rs had to make way for the Rebbe to get to the train. \u201cThis was the toughest moment. We all knew that the Rebbe was leaving us, and we wondered when we would see him again,\u201d remembers Yaakov Abisov. His father turned to the Rebbe in a broken voice and begged, \u201cBless me!\u201d The Rebbe turned around, looking intently at Yaakov\u2019s father, and said, \u201cYour children should remain Jews.\u201d[[95: Zigelbaum, Sippur shel Chag.]]\nStanding on the steps of the train, the Rebbe\u2019s anguish was palpable as he turned to his Chasidim and blessed them one more time. Rabbi Dovid Chein heard his last words. \u201cWhoever wants a bond with me will not make any compromises,\u201d he said. \u201cIt will be very difficult, but that is the condition.\u201d Those words, Chein says, left a lasting impression on his father Yehuda, who was faced with many challenges in the coming years. Whenever it became difficult, he would say, \u201cThe Rebbe told me that whoever wants to be united with him should not make any compromises. I do not want to be separated from the Rebbe.\u201d\nZalman Duchman describes the last moments of the Rebbe\u2019s departure: \u201cWhen the train started moving, it was going very slowly, and all the people were walking after the train. Then the train started going faster and the whole crowd started running. We ran alongside the train. Everybody at the station was crying \u2013 you could see the tears falling, and not one dry eye.\u201d[[96: Duchman, LeSheima Ozen, chap. 2.]] As the train pulled away from the station, the Chasidim sang together the melody \u201cThe Beinoni.\u201d[[97: Composed by Reb Aharon Charitonov, the Rebbe cherished this song and would sing it at farbrengens with his Chasidim. Available at: https://www.youtube.com/watch?v=4I37Gk-1GLs.]]\nMany Chasidim purchased tickets to travel with the Rebbe until the last station before the border. At a number of stations along the route, crowds gathered to bid farewell, and many boarded the train. As it drew closer to the Russian border, the cars rang with the sound of chasidic melodies marking the Russian Chasidim\u2019s last moments with the Rebbe.\nWhile the Rebbe was making his way to Riga, Rabbi Yisrael Jacobson was camped out in the offices of the Kramer brothers in New York. He had been pleading with them to wire $4,000 (the equivalent of $60,000 today) to Mordechai Dubin in Riga. The Rebbe\u2019s relocation had been expensive, pressing debts lingered from his incarceration, and the operation of the underground educational system in Russia required ongoing support. In New York, Rabbi Eliyahu Simpson[[98: Rabbi Eliyahu Simpson (1889\u20131976) was one of the key figures in the development of Chabad in the United States. He studied in the yeshivah in Lubavitch, where he became one of the chozrim (those who memorized and transcribed the maamarim) of the Rebbe Rashab. In 1923, he immigrated to the United States, where he served as the rabbi of the Chabad synagogue in Boro Park. After the arrival of the Rebbe Rayatz in 1940, he became a secretary to the Rebbe.]] had secured s", "tags": [{"start": 2933, "end": 2939, "entity_id": "person.yosef_yitzchak"}, {"start": 2782, "end": 2788, "entity_id": "person.shalom_dovber"}, {"start": 2672, "end": 2681, "entity_id": "place.lubavitch"}, {"start": 2189, "end": 2197, "entity_id": "place.new_york"}, {"start": 2493, "end": 2501, "entity_id": "place.new_york"}, {"start": 2943, "end": 2947, "entity_id": "time.1940"}]}