{"pdf_page": 220, "book_page": 202, "chapter": 7, "text": " his side. The police broke up the fight.\u201d[[29: Quoted in Rotenberg, Masa HaRebbe BeEretz HaKodesh, 68.]] In a letter to his family in Riga, the Rebbe wrote, \u201cThe flyers were spread out by the thousands. It is unnecessary to say what kind of fire they ignited.\u201d[[30: Letter written by the Rebbe from the New Central Hotel upon his arrival in Jerusalem.]] He added that his son-in-law the Rashag made a major diplomatic effort to mitigate the damage, finalizing the meeting with Rabbi Kook. That first afternoon, the Rebbe prayed at the Western Wall, a portion of the historic wall that surrounded the Temple Mount in ancient times. The Rebbe made his way on foot through the Old City, accompanied by hundreds of people. A crowd of 1,500 eventually filled the open space in front of the Wall, which was then much smaller than the present broad plaza.[[31: For centuries, the Arabs permitted Jews to pray only in a small area in front of part of the Western Wall. During the British Mandate, Jews were forbidden to blow shofar at the Wall. In 1967, after the liberation of Jerusalem, the area in front of the Wall was cleared, and the broad plaza that is there today was created. The Wall stretches through the Old City; much of it still blocked today by existing structures. Its total length is 1,601 feet.]] Hundreds more looked on from surrounding rooftops. It was a deeply emotional moment for the Rebbe. \u201cI cried hot tears,\u201d he wrote in a private correspondence to his family.[[32: Letter written by the Rebbe from the New Central Hotel upon his arrival in Jerusalem.]] \u201cWe were in a higher world. No matter how much you believe, no matter how you believe, in such a holy moment, standing next to the Wall of the Beit HaMikdash (the Holy Temple), everything changes. Religious or not, we completely change.\u201d The Rebbe explained that \u201ceverything is elevated as the heart beseeches G-d for mercy.\u201d Most heavily on the Rebbe\u2019s mind at that time was the welfare of the Jews in Russia. \u201cOceans of tears open up as I feel the plight of our dear students, the Chasidim, and their wives and families, and I ponder their spiritual and physical predicament.\u201d In Jerusalem, he visited with Rabbi Sonnenfeld, the chief Sephardic Rabbi Yaakov Meir, and other Jewish leaders. He met with Rabbi Avraham Yitzchak Kook three times \u2013 more than anyone else. The first visit took place in Rabbi Kook\u2019s home on Friday afternoon, where he was greeted by a delegation of rabbis. The second meeting was when Rabbi Kook returned the visit to the Rebbe\u2019s hotel after Shabbat. Their final visit took place before the Rebbe\u2019s departure. Rabbi Kook\u2019s mother[[33: Zlata Perl Kook was 86 at the time of the Rebbe\u2019s visit. She asked the Rebbe for a blessing, and the Rebbe responded by blessing her with long life. She had given her son, Rabbi Kook, a yarmulke that belonged to the third Rebbe, Rabbi Menachem Mendel, the Tzemach Tzedek. Rabbi Kook told the Rebbe that he usually wore it on the High Holidays, but he wore it that", "tags": [{"start": 2872, "end": 2887, "entity_id": "person.menachem_mendel"}]}