{"pdf_page": 233, "book_page": 215, "chapter": 7, "text": "ote that the Rebbe was able to create a mechanism to overcome this problem by providing the funds to Jews in Riga who could not transfer assets beyond the borders of Russia, and then getting rubles from them in Russia.]] Hyman noted that the Rebbe had created a reliable mechanism to secretly transfer funds to Russia. He referred to the Rebbe as \u201cour friend,\u201d never actually using his name. The Rebbe was deeply impressed with Adler, writing to his wife back in Riga, \u201cHe is very serious, with a scholarly face, and great Jewish sensitivity.\u201d[[90: Letter to the Rebbe\u2019s wife.]] They met again a month later. In an internal JDC memo describing the meetings, Adler notes the difficulties of religious life in Russia and the economic woes and is clearly sympathetic to the Rebbe and open to ideas on how to legally transfer funds.[[91: Memorandum of Dr. Cyrus Adler on the meeting of October 9, 1929. JDC Archives.]] At the second meeting, Adler assured the Rebbe that the JDC would help in a significant way, but it would be done secretly.[[92: Igrot Kodesh, vol. 11.]] That commitment was not honored. It was Felix Warburg, chair of the JDC, who disagreed with the Rebbe on the best strategy to help Russian Jews. Warburg was an American banker who supported the partnership with the Soviets in transferring Jews to communal farms.[[93: \u201cWarburg Pledges $1,000,000 to Fund,\u201d New York Times archives, available at: https://www.nytimes.com/1928/04/25/archives/warburg-pledges-1000000-to-fund-will-be-used-to-establish-jews-on.html?auth=link-dismiss-google1tap.]] In 1927, he traveled to Russia, meeting the Rebbe and a delegation of rabbis twice and promising help that did not materialize.[[94: Igrot Kodesh 1:516. In a long letter, the Rebbe describes the history of his efforts for Soviet Jewry. He discusses the meeting with Warburg on page 534.]] Warburg also visited the agricultural colonies and was impressed as he witnessed Jews lining up with farming utensils, looking like they were creating a new life. The Communists put on a good show when he toured the farm towns named after him, Warburg-4 and Warburg-5.[[95: \u201cFelix M. Warburg is Honored by Jewish Colonists in Russia,\u201d JTA, May 18, 1927, available at: https://www.jta.org/1927/05/18/archive/felix-m-warburg-is-honored-by-jewish-colonists-in-russia.]] His brief, staged visit inspired him to become a champion of forced collectivization. \u201cFor a man pampered with luxury, he responded to those threadbare outposts with the glad-handing gusto of a politician in the hustings,\u201d[[96: Ron Chernow, The Warburgs: The Twentieth-Century Odyssey of a Remarkable Jewish Family (Vintage Books, 2003), 294.]] wrote Ron Chernow, Warburg\u2019s biographer. \u201cThe settlements evolved into a bizarre hybrid of Park Avenue charity and Marxist agriculture,\u201d with wealthy Jews of New York partnering with the Communists, funding their goal of socialism. Uprooted from their friends, relatives, and community, Russian Jews were denied the individual right to ch", "tags": [{"start": 1375, "end": 1383, "entity_id": "place.new_york"}, {"start": 2820, "end": 2828, "entity_id": "place.new_york"}, {"start": 1564, "end": 1568, "entity_id": "time.1927"}, {"start": 2198, "end": 2202, "entity_id": "time.1927"}, {"start": 2238, "end": 2242, "entity_id": "time.1927"}]}