{"pdf_page": 242, "book_page": 224, "chapter": 7, "text": " in each for about a week. He spent three months in Chicago, where there was a large Chabad community. He made shorter stops in Springfield and Worcester, Massachusetts, and in other areas of New York such as the Bronx. The furthest western city that the Rebbe visited was St. Louis. He arrived there on Sunday, May 4, and stayed for ten days. In every city, the Rebbe was welcomed by crowds of thousands thronging the train stations. The Yiddish daily The Jewish Record displayed a six-column banner headline over the front page announcing his reception in St. Louis. \u201cSuch a large crowd consisting of thousands of men, women, and children has never been witnessed at any reception accorded to a Jewish leader visiting our city.\u201d[[142: The Jewish Record, May 9, 1930.]] The Detroit Free Press reported that when the Rebbe arrived there, \u201cthousands thronged the lobby of Michigan Central Station and overflowed the streets.\u201d[[143: Detroit Free Press, April 28, 1930.]] From the train station, a procession of \u201cmore than ten thousand escorted the Rebbe to the Emanual Synagogue\u201d in Detroit\u2019s Jewish neighborhood. Chicago\u2019s Morning Journal described how a boisterous crowd of \u201cfifteen thousand welcomed the Lubavitcher Rebbe in LaSalle Street Station.\u201d[[144: February 10, 1930.]] The Chicago Courier noted that the crowds were comprised of \u201cold and young, men and women.\u201d[[145: Chicago Courier, February 11, 1930, reprinted in Levin, Toldot Chabad BeArtzot HaBrit, 67.]] It took police half an hour to make a path for the Rebbe and his entourage to exit, after which, wrote the Morning Journal, \u201ca large parade of hundreds of cars accompanied the Rebbe.\u201d The American Jewish community included many Eastern European immigrants who had a great respect for chasidic Rebbes and distinguished rabbinic scholars. The Rebbe was admired for fearlessly standing up to the Russians, and he was respected for his piousness as a chasidic Rebbe. That, together with his genuine concern for all Jews regardless of their background, made the Rebbe a figure greatly adored. But the Rebbe himself was distressed by the honors bestowed on him. On the day of his arrival in a city where he would invariably be greeted by large crowds, he would fast, seeking spiritual refinement.[[146: Jacobson, Zikhron Livnei Yisrael, 181. Jacobson notes that the Rebbe lost weight during these visits.]] As he remarked to one of his close Chasidim, Rabbi Nissan Telushkin, \u201cHonor should cause you to diminish yourself.\u201d In each city there would be banquets, major speaking events, and receptions. Late one night, after one of these gala dinners, the Rebbe wrote to his wife, \u201cIt\u2019s midnight. I just came from a banquet, I must say to you with a heavy heart. Every time I am at a banquet arranged in my honor, it brings a very vochedik [Yiddish: mundane] feeling.\u2026I don\u2019t feel good or comfortable, not from the speeches which I listen to, nor from the rousing ovations which are made for me or the praises and the falsehoods which are s", "tags": [{"start": 1205, "end": 1214, "entity_id": "place.lubavitch"}, {"start": 192, "end": 200, "entity_id": "place.new_york"}]}