{"pdf_page": 345, "book_page": 327, "chapter": 10, "text": "nent scholars who came on that ship included Rabbi Pinchas Hirschsprung, who was appointed Montreal\u2019s chief rabbi in 1969.]] Tragically, most of those who stayed spent the war years in Shanghai.\u201d[[102: Some of the students of the Mir Yeshivah waited and took the next ship. Sadly, the war broke out while they were traveling, and they were interned in the Philippines, where they suffered greatly. Memoir of Rabbi Yitzchak Hendel.]] In San Francisco, the refugees were escorted by US officials to Chicago by train, and then on to Canada. They reached the Montreal train station on Friday, October 24, and the community welcomed them with open arms. Rabbi Yisrael Jacobson was also at the train station, sent by the Rebbe with instructions for the students. \u201cHe told us that we were to establish a yeshivah,\u201d recalled Tzvi Hirsh Kotlarsky.[[103: Zaklikowski, The People\u2019s Rabbi.]] On Saturday night, at a community reception for the students, Rabbi Jacobson surprised the crowd by announcing the opening of Yeshivas Tomchei Temimim the very next day.[[104: Memoir of Rabbi Yitzchak Hendel.]] Jacobson\u2019s unilateral announcement sparked a debate in Montreal. Local leaders had envisioned opening one yeshivah for all the students, not two separate ones. Judah Albert, president of Montreal\u2019s Chabad synagogue, asserted, \u201cLubavitch has its own principles, be it in learning and teaching, be it in their general outlook to Judaism in their chasidic way of life.\u201d[[105: There had been a community meeting upon the arrival of the students to discuss the issue, and there was a concern that supporting two institutions would be challenging. There was also a degree of opposition to the traditional religious education offered by the yeshivah. With time, the community saw its value. In 1942, S. Greenfeld, president of the Federation of Polish Jews of Canada, who had strongly opposed having two yeshivas, publicly stated that Rabbi Jacobson had been correct. See Zaklikowski, The People\u2019s Rabbi, part IV.]] Two yeshivas opened, Tomchei Temimim and Mercaz HaTorah.[[106: By 1954, Mercaz HaTorah had 140 students. In the mid-1980s, Mercaz HaTorah merged with the newly established Yeshivah Gedolah and today is a major center of Jewish scholarship in Montreal. The Chabad yeshivah became the foundation for Chabad\u2019s growth in the city. Today Montreal boasts a large network of Chabad institutions, including schools, synagogues, and community and campus centers. The yeshivah continues to be a center of learning till today. See Steven Lapidus, \u201cMemoirs of a Refugee: The Travels and Travails of Rabbi Pinchas Hirschsprung,\u201d available at: file:///C:/Users/rabbi/Downloads/editorcjs,+Vol+27,+8,+Lapidus.pdf.]] Both flourished, transforming Montreal\u2019s Jewish community. To survive, the new yeshivah needed financial support. Hirsch Wolofsky, the opinionated editor of the Yiddish newspaper The Canadian Eagle, asked Samuel Bronfman, Seagram\u2019s owner and Montreal\u2019s leading Jewish philanthropist, \u201cAre you going t", "tags": [{"start": 1318, "end": 1327, "entity_id": "place.lubavitch"}]}